{"tablons": {"tablon": [
    {
        "campos-adicionales": "",
        "categorias": {"categoria": [
            {
                "content": "Tablón Admón. del Estado",
                "id": 524
            },
            {
                "content": "Sede electrónica",
                "id": 162
            }
        ]},
        "descripcion": {},
        "documento": "http://www.gijon.es/multimedia_objects/download?object_type=document&object_id=208372",
        "identificador": 80028,
        "locale": "es",
        "numero-de-registro": 2017000093,
        "organizacion-remitente": "Confederación Hidrográfica del Duero",
        "portales": {"portal": {
            "content": "sedeelectronica.gijon.es",
            "id": 45
        }},
        "send": "fecha-actualizacion2017-03-08 13:06:01 +0100",
        "titulo": "Exptes. 36/2017 y 40/2017, en materia de inicio de procedimiento de extinción de derechos de aprovechamiento de aguas por caducidad.",
        "url": "http://www.gijon.es/tablons/show/80028-exptes-36-2017-y-40-2017-en-materia-de-inicio-de-procedimiento-de-extincion-de-derechos-de-aprovechamiento-de-aguas-por-caducidad"
    },
    {
        "campos-adicionales": "",
        "categorias": {"categoria": [
            {
                "content": "Tablón Admón. del Estado",
                "id": 524
            },
            {
                "content": "Sede electrónica",
                "id": 162
            }
        ]},
        "descripcion": {},
        "documento": "http://www.gijon.es/multimedia_objects/download?object_type=document&object_id=208127",
        "identificador": 80017,
        "locale": "es",
        "numero-de-registro": 2017000082,
        "organizacion-remitente": "Instituto de Vivienda, Infraestructura y Equipamiento de la Defensa",
        "portales": {"portal": {
            "content": "sedeelectronica.gijon.es",
            "id": 45
        }},
        "send": "fecha-actualizacion2017-03-02 09:26:20 +0100",
        "titulo": "Resolución de anuncio de sucesivas subastas públicas, tercera y cuarta, con proposición económica en sobre cerrado al alza de dos locales sitos en calle Puerto de Tarna número 9, bajo-4 y bajo-5, en Gijón.",
        "url": "http://www.gijon.es/tablons/show/80017-resolucion-de-anuncio-de-sucesivas-subastas-publicas-tercera-y-cuarta-con-proposicion-economica-en-sobre-cerrado-al-alza-de-dos-locales-sitos-en-calle-"
    },
    {
        "campos-adicionales": "",
        "categorias": {"categoria": [
            {
                "content": "Tablón Admón. del Estado",
                "id": 524
            },
            {
                "content": "Sede electrónica",
                "id": 162
            }
        ]},
        "descripcion": {},
        "documento": "http://www.gijon.es/multimedia_objects/download?object_type=document&object_id=208002",
        "identificador": 80013,
        "locale": "es",
        "numero-de-registro": 2017000078,
        "organizacion-remitente": "Ministerio de Hacienda y Función Pública-Delegación Especial de Economía y Hacienda de Asturias-Gijón",
        "portales": {"portal": {
            "content": "sedeelectronica.gijon.es",
            "id": 45
        }},
        "send": "fecha-actualizacion2017-02-27 13:03:34 +0100",
        "titulo": "Anuncio B.O.E 24 de febrero de 2017, resolución en procedimiento para la declaración de la Administración del Estado como heredera abintestato de Doña Mª Amparo Sierra García, expediente 2016 052 00005 AC/ACP",
        "url": "http://www.gijon.es/tablons/show/80013-anuncio-b-o-e-24-de-febrero-de-2017-resolucion-en-procedimiento-para-la-declaracion-de-la-administracion-del-estado-como-heredera-abintestato-de-dona-m"
    },
    {
        "campos-adicionales": "",
        "categorias": {"categoria": [
            {
                "content": "Tablón Admón. del Estado",
                "id": 524
            },
            {
                "content": "Sede electrónica",
                "id": 162
            }
        ]},
        "descripcion": {},
        "documento": "http://www.gijon.es/multimedia_objects/download?object_type=document&object_id=207987",
        "identificador": 80012,
        "locale": "es",
        "numero-de-registro": 2017000077,
        "organizacion-remitente": "Agencia Tributaria-Delegación Especial de Asturias",
        "portales": {"portal": {
            "content": "sedeelectronica.gijon.es",
            "id": 45
        }},
        "send": "fecha-actualizacion2017-02-27 10:14:15 +0100",
        "titulo": "Subasta de bienes nº S2017R3386001002 propiedad de GILU, S.L.; se adjunta la relación de bienes a subastar. La citada subasta se celebrará el día 25 de abril de 2017.",
        "url": "http://www.gijon.es/tablons/show/80012-subasta-de-bienes-n-s2017r3386001002-propiedad-de-gilu-s-l-se-adjunta-la-relacion-de-bienes-a-subastar-la-citada-subasta-se-celebrara-el-dia-25-de-abri"
    },
    {
        "campos-adicionales": "",
        "categorias": {"categoria": [
            {
                "content": "Tablón Admón. del Estado",
                "id": 524
            },
            {
                "content": "Sede electrónica",
                "id": 162
            }
        ]},
        "descripcion": {},
        "documento": "http://www.gijon.es/multimedia_objects/download?object_type=document&object_id=207986",
        "identificador": 80011,
        "locale": "es",
        "numero-de-registro": 2017000076,
        "organizacion-remitente": "Agencia Tributaria-Delegación Especial de Asturias",
        "portales": {"portal": {
            "content": "sedeelectronica.gijon.es",
            "id": 45
        }},
        "send": "fecha-actualizacion2017-02-27 10:10:31 +0100",
        "titulo": "Subasta de bienes nº S2017R3386001002 propiedad de Doña María Jesús Carmona Sánchez; dicha subasta se celebrará el día 25 de abril de 2017, se adjuntan los lotes a subastar con la descripción de los bienes.",
        "url": "http://www.gijon.es/tablons/show/80011-subasta-de-bienes-n-s2017r3386001002-propiedad-de-dona-maria-jesus-carmona-sanchez-dicha-subasta-se-celebrara-el-dia-25-de-abril-de-2017-se-adjuntan-lo"
    },
    {
        "campos-adicionales": "",
        "categorias": {"categoria": [
            {
                "content": "Tablón Admón. del Estado",
                "id": 524
            },
            {
                "content": "Sede electrónica",
                "id": 162
            }
        ]},
        "descripcion": {},
        "documento": "http://www.gijon.es/multimedia_objects/download?object_type=document&object_id=205878",
        "identificador": 79950,
        "locale": "es",
        "numero-de-registro": 2017000015,
        "organizacion-remitente": "Demarcación de Costas en Asturias",
        "portales": {"portal": {
            "content": "sedeelectronica.gijon.es",
            "id": 45
        }},
        "send": "fecha-actualizacion2017-01-13 08:36:32 +0100",
        "titulo": "Anuncio sobre solicitudes de autorización para explotación de servicios de temporada de verano en playas de dominio público marítimo terrestre, durante el presente año 2017 y posteriores por parte de particulares. Referencia V-20/16.",
        "url": "http://www.gijon.es/tablons/show/79950-anuncio-sobre-solicitudes-de-autorizacion-para-explotacion-de-servicios-de-temporada-de-verano-en-playas-de-dominio-publico-maritimo-terrestre-durante-"
    },
    {
        "campos-adicionales": "",
        "categorias": {"categoria": [
            {
                "content": "Tablón Admón. del Estado",
                "id": 524
            },
            {
                "content": "Sede electrónica",
                "id": 162
            }
        ]},
        "descripcion": {},
        "identificador": 68483,
        "locale": "es",
        "numero-de-registro": {},
        "organizacion-remitente": {},
        "portales": "",
        "send": "fecha-actualizacion2011-07-25 13:26:33 +0200",
        "titulo": "a",
        "url": "http://www.gijon.es/tablons/show/68483-a"
    },
    {
        "campos-adicionales": "",
        "categorias": {"categoria": [
            {
                "content": "Tablón Admón. del Estado",
                "id": 524
            },
            {
                "content": "Sede electrónica",
                "id": 162
            }
        ]},
        "descripcion": {},
        "identificador": 68482,
        "locale": "es",
        "numero-de-registro": {},
        "organizacion-remitente": {},
        "portales": "",
        "send": "fecha-actualizacion2011-07-25 13:26:13 +0200",
        "titulo": "a",
        "url": "http://www.gijon.es/tablons/show/68482-a"
    }
]}}